inductiva/__init__.py
inductiva/constants.py
inductiva/types.py
inductiva/_cli/__init__.py
inductiva/_cli/ansi_pager.py
inductiva/_cli/loader.py
inductiva/_cli/main.py
inductiva/_cli/utils.py
inductiva/_cli/cmd_auth/__init__.py
inductiva/_cli/cmd_auth/login.py
inductiva/_cli/cmd_auth/logout.py
inductiva/_cli/cmd_containers/__init__.py
inductiva/_cli/cmd_containers/convert.py
inductiva/_cli/cmd_containers/list.py
inductiva/_cli/cmd_containers/remove.py
inductiva/_cli/cmd_containers/upload.py
inductiva/_cli/cmd_logs/__init__.py
inductiva/_cli/cmd_logs/logs.py
inductiva/_cli/cmd_projects/__init__.py
inductiva/_cli/cmd_projects/download.py
inductiva/_cli/cmd_projects/list.py
inductiva/_cli/cmd_quotas/__init__.py
inductiva/_cli/cmd_quotas/list.py
inductiva/_cli/cmd_resources/__init__.py
inductiva/_cli/cmd_resources/cost.py
inductiva/_cli/cmd_resources/info.py
inductiva/_cli/cmd_resources/list.py
inductiva/_cli/cmd_resources/start.py
inductiva/_cli/cmd_resources/terminate.py
inductiva/_cli/cmd_simulators/__init__.py
inductiva/_cli/cmd_simulators/list.py
inductiva/_cli/cmd_storage/__init__.py
inductiva/_cli/cmd_storage/download.py
inductiva/_cli/cmd_storage/export.py
inductiva/_cli/cmd_storage/list.py
inductiva/_cli/cmd_storage/remove.py
inductiva/_cli/cmd_storage/size.py
inductiva/_cli/cmd_storage/upload.py
inductiva/_cli/cmd_storage/cmd_bucket/__init__.py
inductiva/_cli/cmd_storage/cmd_bucket/list.py
inductiva/_cli/cmd_task_runner/__init__.py
inductiva/_cli/cmd_task_runner/launch.py
inductiva/_cli/cmd_task_runner/remove.py
inductiva/_cli/cmd_tasks/__init__.py
inductiva/_cli/cmd_tasks/download.py
inductiva/_cli/cmd_tasks/info.py
inductiva/_cli/cmd_tasks/kill.py
inductiva/_cli/cmd_tasks/last_modified_file.py
inductiva/_cli/cmd_tasks/list.py
inductiva/_cli/cmd_tasks/list_files.py
inductiva/_cli/cmd_tasks/tail.py
inductiva/_cli/cmd_tasks/top.py
inductiva/_cli/cmd_user/__init__.py
inductiva/_cli/cmd_user/info.py
inductiva/api/__init__.py
inductiva/api/methods.py
inductiva-0.18.9.dist-info/licenses/LICENSE
inductiva-0.18.9.dist-info/METADATA
inductiva-0.18.9.dist-info/WHEEL
inductiva-0.18.9.dist-info/entry_points.txt
inductiva-0.18.9.dist-info/top_level.txt
inductiva-0.18.9.dist-info/RECORD
