Metadata-Version: 2.4
Name: inductiva
Version: 0.18.9
Summary: Python client for the Inductiva API
Home-page: https://github.com/inductiva/inductiva
Author: Inductiva Research Labs
Author-email: contact@inductiva.ai
Classifier: Programming Language :: Python :: 3
Classifier: Operating System :: OS Independent
Requires-Python: >=3.9
License-File: LICENSE
Requires-Dist: jinja2
Requires-Dist: tabulate
Requires-Dist: tqdm
Requires-Dist: websocket-client
Requires-Dist: fsspec
Requires-Dist: requests
Requires-Dist: aiohttp
Requires-Dist: nest_asyncio
Requires-Dist: urllib3<3.0.0,>=2.1.0
Requires-Dist: python-dateutil>=2.8.2
Requires-Dist: pydantic>=2
Requires-Dist: typing-extensions>=4.7.1
Requires-Dist: pytimeparse2
Requires-Dist: docker
Requires-Dist: aiortc
Provides-Extra: aws
Requires-Dist: awscli; extra == "aws"
Requires-Dist: boto3; extra == "aws"
Dynamic: license-file
Dynamic: requires-dist
